<?xml version="1.0" encoding="UTF-8"?><record_update>
    <sys_choice action="INSERT_OR_UPDATE" field="connection_status" table="x_tekso_twxapp01_setup" version="3">
        <sys_choice_set action="INSERT_OR_UPDATE">
            <element>connection_status</element>
            <name>x_tekso_twxapp01_setup</name>
            <sys_class_name>sys_choice_set</sys_class_name>
            <sys_created_by>robin</sys_created_by>
            <sys_created_on>2020-01-30 10:34:33</sys_created_on>
            <sys_id>1e29075bdb26001041d08f38139619c1</sys_id>
            <sys_mod_count>0</sys_mod_count>
            <sys_name>connection_status</sys_name>
            <sys_package display_value="Application 1" source="x_tekso_twxapp01">993be4b2db62085035a38a72399619a7</sys_package>
            <sys_policy/>
            <sys_scope display_value="Application 1">993be4b2db62085035a38a72399619a7</sys_scope>
            <sys_update_name>sys_choice_x_tekso_twxapp01_setup_connection_status</sys_update_name>
            <sys_updated_by>robin</sys_updated_by>
            <sys_updated_on>2020-01-30 10:34:33</sys_updated_on>
        </sys_choice_set>
        <sys_choice action="INSERT_OR_UPDATE">
            <dependent_value/>
            <element>connection_status</element>
            <hint/>
            <inactive>false</inactive>
            <label>Connection Requires Testing</label>
            <language>en</language>
            <name>x_tekso_twxapp01_setup</name>
            <sequence/>
            <sys_created_by>robin</sys_created_by>
            <sys_created_on>2020-01-30 10:36:33</sys_created_on>
            <sys_domain>global</sys_domain>
            <sys_domain_path>/</sys_domain_path>
            <sys_id>2f79c31bdb26001041d08f3813961941</sys_id>
            <sys_mod_count>0</sys_mod_count>
            <sys_updated_by>robin</sys_updated_by>
            <sys_updated_on>2020-01-30 10:36:33</sys_updated_on>
            <value>Connection Requires Testing</value>
        </sys_choice>
        <sys_choice action="INSERT_OR_UPDATE">
            <dependent_value/>
            <element>connection_status</element>
            <hint/>
            <inactive>false</inactive>
            <label>Failed</label>
            <language>en</language>
            <name>x_tekso_twxapp01_setup</name>
            <sequence/>
            <sys_created_by>robin</sys_created_by>
            <sys_created_on>2020-01-30 10:35:18</sys_created_on>
            <sys_domain>global</sys_domain>
            <sys_domain_path>/</sys_domain_path>
            <sys_id>5b29075bdb26001041d08f38139619c4</sys_id>
            <sys_mod_count>0</sys_mod_count>
            <sys_updated_by>robin</sys_updated_by>
            <sys_updated_on>2020-01-30 10:35:18</sys_updated_on>
            <value>Failed</value>
        </sys_choice>
        <sys_choice action="INSERT_OR_UPDATE">
            <dependent_value/>
            <element>connection_status</element>
            <hint/>
            <inactive>false</inactive>
            <label>Missing Connection Details</label>
            <language>en</language>
            <name>x_tekso_twxapp01_setup</name>
            <sequence/>
            <sys_created_by>robin</sys_created_by>
            <sys_created_on>2020-01-30 10:35:44</sys_created_on>
            <sys_domain>global</sys_domain>
            <sys_domain_path>/</sys_domain_path>
            <sys_id>2649471bdb26001041d08f38139619f9</sys_id>
            <sys_mod_count>0</sys_mod_count>
            <sys_updated_by>robin</sys_updated_by>
            <sys_updated_on>2020-01-30 10:35:44</sys_updated_on>
            <value>Missing Connection Details</value>
        </sys_choice>
        <sys_choice action="INSERT_OR_UPDATE">
            <dependent_value/>
            <element>connection_status</element>
            <hint/>
            <inactive>false</inactive>
            <label>OK</label>
            <language>en</language>
            <name>x_tekso_twxapp01_setup</name>
            <sequence/>
            <sys_created_by>robin</sys_created_by>
            <sys_created_on>2020-01-30 10:34:33</sys_created_on>
            <sys_domain>global</sys_domain>
            <sys_domain_path>/</sys_domain_path>
            <sys_id>6f09075bdb26001041d08f38139619bd</sys_id>
            <sys_mod_count>0</sys_mod_count>
            <sys_updated_by>robin</sys_updated_by>
            <sys_updated_on>2020-01-30 10:34:33</sys_updated_on>
            <value>OK</value>
        </sys_choice>
        <sys_choice action="INSERT_OR_UPDATE">
            <dependent_value/>
            <element>connection_status</element>
            <hint/>
            <inactive>false</inactive>
            <label>Sending Process Starting - Please Wait</label>
            <language>en</language>
            <name>x_tekso_twxapp01_setup</name>
            <sequence/>
            <sys_created_by>robin</sys_created_by>
            <sys_created_on>2020-03-19 13:33:55</sys_created_on>
            <sys_domain>global</sys_domain>
            <sys_domain_path>/</sys_domain_path>
            <sys_id>65188c9fdb6f0c1041d08f381396199f</sys_id>
            <sys_mod_count>0</sys_mod_count>
            <sys_updated_by>robin</sys_updated_by>
            <sys_updated_on>2020-03-19 13:33:55</sys_updated_on>
            <value>Sending Process Starting - Please Wait</value>
        </sys_choice>
        <sys_choice action="INSERT_OR_UPDATE">
            <dependent_value/>
            <element>connection_status</element>
            <hint/>
            <inactive>false</inactive>
            <label>Testing Connection - Please Wait</label>
            <language>en</language>
            <name>x_tekso_twxapp01_setup</name>
            <sequence/>
            <sys_created_by>robin</sys_created_by>
            <sys_created_on>2020-03-19 13:33:34</sys_created_on>
            <sys_domain>global</sys_domain>
            <sys_domain_path>/</sys_domain_path>
            <sys_id>ac0884d3dbaf0c1041d08f3813961925</sys_id>
            <sys_mod_count>0</sys_mod_count>
            <sys_updated_by>robin</sys_updated_by>
            <sys_updated_on>2020-03-19 13:33:34</sys_updated_on>
            <value>Testing Connection - Please Wait</value>
        </sys_choice>
    </sys_choice>
</record_update>
